MANIFEST.in
README.md
requirements.txt
setup.py
reveal_user_classification/__init__.py
reveal_user_classification/common.py
reveal_user_classification.egg-info/PKG-INFO
reveal_user_classification.egg-info/SOURCES.txt
reveal_user_classification.egg-info/dependency_links.txt
reveal_user_classification.egg-info/entry_points.txt
reveal_user_classification.egg-info/requires.txt
reveal_user_classification.egg-info/top_level.txt
reveal_user_classification/entry_points/__init__.py
reveal_user_classification/entry_points/prototype_user_network_profile_classifier.py
reveal_user_classification/entry_points/user_network_profile_classifier.py
reveal_user_classification/preprocess/__init__.py
reveal_user_classification/preprocess/insight/__init__.py
reveal_user_classification/preprocess/insight/insight_curation_util.py
reveal_user_classification/preprocess/insight/insight_multiview_util.py
reveal_user_classification/preprocess/insight/preprocess_curation_datasets.py
reveal_user_classification/preprocess/insight/preprocess_multiview_datasets.py
reveal_user_classification/preprocess/snow/__init__.py
reveal_user_classification/preprocess/snow/make_snow_2014_graph_dataset.py
reveal_user_classification/preprocess/snow/snow_2014_graph_dataset_util.py
reveal_user_classification/reveal/__init__.py
reveal_user_classification/reveal/integration.py
reveal_user_classification/reveal/utility.py