Metadata-Version: 1.1
Name: reveal-user-classification
Version: 0.2.5
Summary: Performs user classification into labels using a set of seed Twitter users with known labels andthe structure of the interaction network between them.
Home-page: https://github.com/MKLab-ITI/reveal-user-classification
Author: Georgios Rizos
Author-email: georgerizos@iti.gr
License: Apache
Keywords: online-social-network user-classification Reveal-FP7
Platform: UNKNOWN
Classifier: Development Status :: 2 - Pre-Alpha
Classifier: Intended Audience :: Science/Research
Classifier: License :: OSI Approved :: Apache Software License
Classifier: Natural Language :: English
Classifier: Operating System :: Unix
Classifier: Programming Language :: Python
Classifier: Programming Language :: Python :: 3
Classifier: Programming Language :: Python :: 3.4
Classifier: Programming Language :: Python :: 3 :: Only
Classifier: Programming Language :: Python :: Implementation
Classifier: Programming Language :: Python :: Implementation :: CPython
Classifier: Topic :: Scientific/Engineering :: Information Analysis
